openai_schema/__init__.py
openai_schema/chat/__init__.py
openai_schema/chat/completion.py
openai_schema-0.1.1.dist-info/LICENSE
openai_schema-0.1.1.dist-info/METADATA
openai_schema-0.1.1.dist-info/WHEEL
openai_schema-0.1.1.dist-info/RECORD
