Metadata-Version: 2.1
Name: openai-schema
Version: 0.1.1
Summary: 
Author: Masum Billal
Author-email: billalmasum93@gmail.com
Requires-Python: >=3.11,<4.0
Classifier: Programming Language :: Python :: 3
Classifier: Programming Language :: Python :: 3.11
Classifier: Programming Language :: Python :: 3.12
Requires-Dist: openai (>=1.28.1,<2.0.0)
Requires-Dist: pydantic (>=2.7.1,<3.0.0)
